valet_agent/__init__.py
valet_agent/beacondb.py
valet_agent/cli.py
valet_agent/client.py
valet_agent/collector.py
valet_agent/commands.py
valet_agent/config.py
valet_agent/enrollment.py
valet_agent/hardware.py
valet_agent/main.py
valet_agent/mqtt.py
valet_agent/py.typed
valet_agent/wifi.py
valet_agent-2026.1.20.dist-info/METADATA
valet_agent-2026.1.20.dist-info/WHEEL
valet_agent-2026.1.20.dist-info/entry_points.txt
valet_agent-2026.1.20.dist-info/licenses/LICENSE
valet_agent-2026.1.20.dist-info/RECORD
