Metadata-Version: 2.4
Name: valet-agent
Version: 2026.1.20
Summary: DeviceValet Linux Agent - Fleet management daemon for Linux desktops, servers, and IoT devices
Project-URL: Homepage, https://github.com/supported-systems/devicevalet
Project-URL: Documentation, https://docs.devicevalet.io
Project-URL: Repository, https://github.com/supported-systems/devicevalet
Project-URL: Issues, https://github.com/supported-systems/devicevalet/issues
Project-URL: Changelog, https://github.com/supported-systems/devicevalet/blob/main/agent-linux/CHANGELOG.md
Author-email: Ryan Malloy <ryan@supported.systems>
Maintainer-email: Ryan Malloy <ryan@supported.systems>
License: MIT
License-File: LICENSE
Keywords: agent,device-management,endpoint-management,fleet,iot,linux,mdm,monitoring,telemetry
Classifier: Development Status :: 4 - Beta
Classifier: Environment :: Console
Classifier: Environment :: No Input/Output (Daemon)
Classifier: Intended Audience :: Information Technology
Classifier: Intended Audience :: System Administrators
Classifier: License :: OSI Approved :: MIT License
Classifier: Operating System :: POSIX :: Linux
Classifier: Programming Language :: Python :: 3
Classifier: Programming Language :: Python :: 3.10
Classifier: Programming Language :: Python :: 3.11
Classifier: Programming Language :: Python :: 3.12
Classifier: Programming Language :: Python :: 3.13
Classifier: Topic :: System :: Hardware
Classifier: Topic :: System :: Monitoring
Classifier: Topic :: System :: Systems Administration
Classifier: Typing :: Typed
Requires-Python: >=3.10
Requires-Dist: httpx>=0.28.0
Requires-Dist: paho-mqtt>=2.1.0
Requires-Dist: psutil>=6.0.0
Requires-Dist: pydantic-settings>=2.7.0
Requires-Dist: pydantic>=2.10.0
Provides-Extra: dev
Requires-Dist: mypy>=1.14.0; extra == 'dev'
Requires-Dist: pytest-cov>=6.0.0; extra == 'dev'
Requires-Dist: pytest>=8.0.0; extra == 'dev'
Requires-Dist: ruff>=0.9.0; extra == 'dev'
